mlops7sem_hw2/.gitignore
mlops7sem_hw2/__init__.py
mlops7sem_hw2/config.py
mlops7sem_hw2/dataset.py
mlops7sem_hw2/decisiontree_params.yaml
mlops7sem_hw2/features.py
mlops7sem_hw2/logreg_params.yaml
mlops7sem_hw2/params.yaml
mlops7sem_hw2/params_docker.yaml
mlops7sem_hw2/plots.py
mlops7sem_hw2/randomforest_params.yaml
mlops7sem_hw2/testing.py
mlops7sem_hw2/testing_github_actions.py
mlops7sem_hw2/modeling/__init__.py
mlops7sem_hw2/modeling/predict.py
mlops7sem_hw2/modeling/train.py
mlops7sem_hw2-0.0.1.dist-info/LICENSE
mlops7sem_hw2-0.0.1.dist-info/WHEEL
mlops7sem_hw2-0.0.1.dist-info/METADATA
mlops7sem_hw2-0.0.1.dist-info/RECORD
