Metadata-Version: 2.3
Name: mlops7sem_hw2
Version: 0.0.1
Summary: A short description of the project.
Author: Maria Ulyanova
Requires-Python: ~=3.11.8
Classifier: Programming Language :: Python :: 3
Classifier: License :: OSI Approved :: MIT License
